setup.py
rangerbotapi/__init__.py
rangerbotapi/get.py
rangerbotapi.egg-info/PKG-INFO
rangerbotapi.egg-info/SOURCES.txt
rangerbotapi.egg-info/dependency_links.txt
rangerbotapi.egg-info/top_level.txt