Metadata-Version: 2.1
Name: rangerbotapi
Version: 0.0.1
Summary: Rangerbot api in python
Home-page: UNKNOWN
Author: Joci12
Author-email: <csutak.jozsef.lorant.86@gmail.com>
License: UNKNOWN
Keywords: python,ranger,rangerbot,aki26,joci,package
Platform: UNKNOWN
Classifier: Programming Language :: Python :: 3
